Workbook

Sheet Como usar
A1: Como usar · Notinha
B4: O QUE A NOTINHA PREENCHE
B5: • O bloco "Gastos do Mês" (colunas A–E) de cada aba mensal: cada nota fiscal que você manda no WhatsApp vira uma linha, com Forma e Categoria já coloridas.
B7: O QUE VOCÊ PREENCHE
B8: • Fixos e Cartão de Crédito (colunas G–I).
B9: • Entradas: Salário e Bônus.
B10: • Saídas: só as linhas Reserva e Metas (o quanto você guardou). Débito, Crédito, Pix, Dinheiro e Voucher são somados automaticamente.
B11: • Investimentos: Reserva e Renda fixa.
B12: • Na tabela de categorias, "Valor esperado" é a sua meta de gasto por categoria.
B13: • "Contas a pagar": suas faturas e boletos, com data de vencimento e o checkbox Pago? — é um lembrete do que ainda falta pagar.
B15: SAÍDAS × CONTAS A PAGAR (a diferença)
B16: • SAÍDAS por forma de pagamento = o que JÁ saiu no mês, somado por forma (Débito, Crédito, Pix...). É o que fecha o seu Saldo.
B17: • CONTAS A PAGAR = o que ainda VAI sair (faturas/boletos a vencer). É um checklist, não entra no Saldo.
... B28: Célula de preenchimento

Sheet Janeiro
A1: Janeiro · Notinha 2026
A3: GASTOS DO MÊS — lançados pela Notinha | D3: Total do mês | E3: =SUM(E5:E64) -> 649.6 | G3: FIXOS (você preenche) | I3: =SUM(I5:I12) -> 0 | K3: GASTOS DO MÊS POR CATEGORIA
A4: Nome | B4: Data | C4: Forma | D4: Categoria | E4: Valor | G4: Forma | H4: Categoria | I4: Valor | K4: Categoria | L4: Valor esperado | M4: Valor gasto | N4: %
A5: Supermercado (exemplo) | B5: 46027 | C5: Débito | D5: Mercado | E5: 312.45 | K5: Alimentação | M5: =SUMIF($D$5:$D$64,$K5,$E$5:$E$64) -> 56.9 | N5: =IFERROR(M5/$E$3,0) -> 0.087592365
A6: Restaurante (exemplo) | B6: 46030 | C6: Crédito | D6: Alimentação | E6: 56.9 | K6: Mercado | M6: =SUMIF($D$5:$D$64,$K6,$E$5:$E$64) -> 312.45 | N6: =IFERROR(M6/$E$3,0) -> 0.4809883
A7: Transporte (exemplo) | B7: 46034 | C7: Pix | D7: Transporte | E7: 18.75 | K7: Farmácia | M7: =SUMIF($D$5:$D$64,$K7,$E$5:$E$64) -> 74.2 | N7: =IFERROR(M7/$E$3,0) -> 0.11422414
A8: Conta de casa (exemplo) | B8: 46037 | C8: Débito | D8: Casa | E8: 187.3 | K8: Combustível | M8: =SUMIF($D$5:$D$64,$K8,$E$5:$E$64) -> 0 | N8: =IFERROR(M8/$E$3,0) -> 0
A9: Farmácia (exemplo) | B9: 46042 | C9: Dinheiro | D9: Farmácia | E9: 74.2 | K9: Transporte | M9: =SUMIF($D$5:$D$64,$K9,$E$5:$E$64) -> 18.75 | N9: =IFERROR(M9/$E$3,0) -> 0.028863916
K10: Vestuário | M10: =SUMIF($D$5:$D$64,$K10,$E$5:$E$64) -> 0 | N10: =IFERROR(M10/$E$3,0) -> 0
K11: Eletrônicos | M11: =SUMIF($D$5:$D$64,$K11,$E$5:$E$64) -> 0 | N11: =IFERROR(M11/$E$3,0) -> 0
K12: Casa | M12: =SUMIF($D$5:$D$64,$K12,$E$5:$E$64) -> 187.3 | N12: =IFERROR(M12/$E$3,0) -> 0.28833128
K13: Saúde | M13: =SUMIF($D$5:$D$64,$K13,$E$5:$E$64) -> 0 | N13: =IFERROR(M13/$E$3,0) -> 0
G14: CARTÃO DE CRÉDITO (você preenche) | I14: =SUM(I16:I23) -> 0 | K14: Lazer | M14: =SUMIF($D$5:$D$64,$K14,$E$5:$E$64) -> 0 | N14: =IFERROR(M14/$E$3,0) -> 0
G15: Forma | H15: Categoria | I15: Valor | K15: Serviços | M15: =SUMIF($D$5:$D$64,$K15,$E$5:$E$64) -> 0 | N15: =IFERROR(M15/$E$3,0) -> 0
K16: Outros | M16: =SUMIF($D$5:$D$64,$K16,$E$5:$E$64) -> 0 | N16: =IFERROR(M16/$E$3,0) -> 0
K17: Total | L17: =SUM(L5:L16) -> 0 | M17: =SUM(M5:M16) -> 649.6 | N17: =IFERROR(M17/$E$3,0) -> 1
K19: CONTAS A PAGAR (faturas)
K20: Descrição | L20: Valor | M20: Vencimento | N20: Pago?
G25: ENTRADAS (você preenche)
G26: Salário
G27: Bônus
G28: Total | I28: =SUM(I26:I27) -> 0
G30: SAÍDAS POR FORMA DE PAGAMENTO
G31: Débito | I31: =SUMIF($C$5:$C$64,$G31,$E$5:$E$64)+SUMIF($G$5:$G$12,$G31,$I$5:$I$12)+SUMIF($G$16:$G$23,$G31,$I$16:$I$23) -> 499.75
G32: Crédito | I32: =SUMIF($C$5:$C$64,$G32,$E$5:$E$64)+SUMIF($G$5:$G$12,$G32,$I$5:$I$12)+SUMIF($G$16:$G$23,$G32,$I$16:$I$23) -> 56.9 | K32: INSIGHTS DO MÊS
G33: Pix | I33: =SUMIF($C$5:$C$64,$G33,$E$5:$E$64)+SUMIF($G$5:$G$12,$G33,$I$5:$I$12)+SUMIF($G$16:$G$23,$G33,$I$16:$I$23) -> 18.75 | K33: Nº de lançamentos | N33: =COUNT($E$5:$E$64) -> 5
G34: Dinheiro | I34: =SUMIF($C$5:$C$64,$G34,$E$5:$E$64)+SUMIF($G$5:$G$12,$G34,$I$5:$I$12)+SUMIF($G$16:$G$23,$G34,$I$16:$I$23) -> 74.2 | K34: Maior compra | N34: =IF(COUNT($E$5:$E$64)=0,0,MAX($E$5:$E$64)) -> 312.45
G35: Voucher | I35: =SUMIF($C$5:$C$64,$G35,$E$5:$E$64)+SUMIF($G$5:$G$12,$G35,$I$5:$I$12)+SUMIF($G$16:$G$23,$G35,$I$16:$I$23) -> 0 | K35: Onde foi a maior compra | N35: =IF($E$3=0,"—",INDEX($A$5:$A$64,MATCH(MAX($E$5:$E$64),$E$5:$E$64,0))) -> Supermercado (exemplo)
G36: Outros | I36: =SUMIF($C$5:$C$64,$G36,$E$5:$E$64)+SUMIF($G$5:$G$12,$G36,$I$5:$I$12)+SUMIF($G$16:$G$23,$G36,$I$16:$I$23) -> 0 | K36: Categoria campeã | N36: =IF($E$3=0,"—",INDEX($K$5:$K$16,MATCH(MAX($M$5:$M$16),$M$5:$M$16,0))) -> Mercado
G37: Reserva | K37: Ticket médio | N37: =IFERROR(AVERAGE($E$5:$E$64),0) -> 129.92
G38: Metas | K38: Gasto médio por dia | N38: =IFERROR($E$3/DAY(EOMONTH(DATE(2026,1,1),0)),0) -> 20.954839
G39: Total de saídas | I39: =SUM(I31:I38) -> 649.6 | K39: % das entradas já gasto | N39: =IFERROR($I$39/$I$28,0) -> 0
G41: INVESTIMENTOS
G42: Reserva
G43: Renda fixa
G44: Total | I44: =SUM(I42:I43) -> 0
G46: SALDO DO MÊS (Entradas − Saídas)
G47: =I28-I39 -> -649.6

Sheet Fevereiro
A1: Fevereiro · Notinha 2026
A3: GASTOS DO MÊS — lançados pela Notinha | D3: Total do mês | E3: =SUM(E5:E64) -> 0 | G3: FIXOS (você preenche) | I3: =SUM(I5:I12) -> 0 | K3: GASTOS DO MÊS POR CATEGORIA
A4: Nome | B4: Data | C4: Forma | D4: Categoria | E4: Valor | G4: Forma | H4: Categoria | I4: Valor | K4: Categoria | L4: Valor esperado | M4: Valor gasto | N4: %
K5: Alimentação | M5: =SUMIF($D$5:$D$64,$K5,$E$5:$E$64) -> 0 | N5: =IFERROR(M5/$E$3,0) -> 0
K6: Mercado | M6: =SUMIF($D$5:$D$64,$K6,$E$5:$E$64) -> 0 | N6: =IFERROR(M6/$E$3,0) -> 0
K7: Farmácia | M7: =SUMIF($D$5:$D$64,$K7,$E$5:$E$64) -> 0 | N7: =IFERROR(M7/$E$3,0) -> 0
K8: Combustível | M8: =SUMIF($D$5:$D$64,$K8,$E$5:$E$64) -> 0 | N8: =IFERROR(M8/$E$3,0) -> 0
K9: Transporte | M9: =SUMIF($D$5:$D$64,$K9,$E$5:$E$64) -> 0 | N9: =IFERROR(M9/$E$3,0) -> 0
K10: Vestuário | M10: =SUMIF($D$5:$D$64,$K10,$E$5:$E$64) -> 0 | N10: =IFERROR(M10/$E$3,0) -> 0
K11: Eletrônicos | M11: =SUMIF($D$5:$D$64,$K11,$E$5:$E$64) -> 0 | N11: =IFERROR(M11/$E$3,0) -> 0
K12: Casa | M12: =SUMIF($D$5:$D$64,$K12,$E$5:$E$64) -> 0 | N12: =IFERROR(M12/$E$3,0) -> 0
K13: Saúde | M13: =SUMIF($D$5:$D$64,$K13,$E$5:$E$64) -> 0 | N13: =IFERROR(M13/$E$3,0) -> 0
G14: CARTÃO DE CRÉDITO (você preenche) | I14: =SUM(I16:I23) -> 0 | K14: Lazer | M14: =SUMIF($D$5:$D$64,$K14,$E$5:$E$64) -> 0 | N14: =IFERROR(M14/$E$3,0) -> 0
G15: Forma | H15: Categoria | I15: Valor | K15: Serviços | M15: =SUMIF($D$5:$D$64,$K15,$E$5:$E$64) -> 0 | N15: =IFERROR(M15/$E$3,0) -> 0
K16: Outros | M16: =SUMIF($D$5:$D$64,$K16,$E$5:$E$64) -> 0 | N16: =IFERROR(M16/$E$3,0) -> 0
K17: Total | L17: =SUM(L5:L16) -> 0 | M17: =SUM(M5:M16) -> 0 | N17: =IFERROR(M17/$E$3,0) -> 0
K19: CONTAS A PAGAR (faturas)
K20: Descrição | L20: Valor | M20: Vencimento | N20: Pago?
G25: ENTRADAS (você preenche)
G26: Salário
G27: Bônus
G28: Total | I28: =SUM(I26:I27) -> 0
G30: SAÍDAS POR FORMA DE PAGAMENTO
G31: Débito | I31: =SUMIF($C$5:$C$64,$G31,$E$5:$E$64)+SUMIF($G$5:$G$12,$G31,$I$5:$I$12)+SUMIF($G$16:$G$23,$G31,$I$16:$I$23) -> 0
G32: Crédito | I32: =SUMIF($C$5:$C$64,$G32,$E$5:$E$64)+SUMIF($G$5:$G$12,$G32,$I$5:$I$12)+SUMIF($G$16:$G$23,$G32,$I$16:$I$23) -> 0 | K32: INSIGHTS DO MÊS
G33: Pix | I33: =SUMIF($C$5:$C$64,$G33,$E$5:$E$64)+SUMIF($G$5:$G$12,$G33,$I$5:$I$12)+SUMIF($G$16:$G$23,$G33,$I$16:$I$23) -> 0 | K33: Nº de lançamentos | N33: =COUNT($E$5:$E$64) -> 0
G34: Dinheiro | I34: =SUMIF($C$5:$C$64,$G34,$E$5:$E$64)+SUMIF($G$5:$G$12,$G34,$I$5:$I$12)+SUMIF($G$16:$G$23,$G34,$I$16:$I$23) -> 0 | K34: Maior compra | N34: =IF(COUNT($E$5:$E$64)=0,0,MAX($E$5:$E$64)) -> 0
G35: Voucher | I35: =SUMIF($C$5:$C$64,$G35,$E$5:$E$64)+SUMIF($G$5:$G$12,$G35,$I$5:$I$12)+SUMIF($G$16:$G$23,$G35,$I$16:$I$23) -> 0 | K35: Onde foi a maior compra | N35: =IF($E$3=0,"—",INDEX($A$5:$A$64,MATCH(MAX($E$5:$E$64),$E$5:$E$64,0))) -> —
G36: Outros | I36: =SUMIF($C$5:$C$64,$G36,$E$5:$E$64)+SUMIF($G$5:$G$12,$G36,$I$5:$I$12)+SUMIF($G$16:$G$23,$G36,$I$16:$I$23) -> 0 | K36: Categoria campeã | N36: =IF($E$3=0,"—",INDEX($K$5:$K$16,MATCH(MAX($M$5:$M$16),$M$5:$M$16,0))) -> —
G37: Reserva | K37: Ticket médio | N37: =IFERROR(AVERAGE($E$5:$E$64),0) -> 0
G38: Metas | K38: Gasto médio por dia | N38: =IFERROR($E$3/DAY(EOMONTH(DATE(2026,2,1),0)),0) -> 0
G39: Total de saídas | I39: =SUM(I31:I38) -> 0 | K39: % das entradas já gasto | N39: =IFERROR($I$39/$I$28,0) -> 0
G41: INVESTIMENTOS
G42: Reserva
G43: Renda fixa
G44: Total | I44: =SUM(I42:I43) -> 0
G46: SALDO DO MÊS (Entradas − Saídas)
G47: =I28-I39 -> 0

Sheet Março
A1: Março · Notinha 2026
A3: GASTOS DO MÊS — lançados pela Notinha | D3: Total do mês | E3: =SUM(E5:E64) -> 0 | G3: FIXOS (você preenche) | I3: =SUM(I5:I12) -> 0 | K3: GASTOS DO MÊS POR CATEGORIA
A4: Nome | B4: Data | C4: Forma | D4: Categoria | E4: Valor | G4: Forma | H4: Categoria | I4: Valor | K4: Categoria | L4: Valor esperado | M4: Valor gasto | N4: %
K5: Alimentação | M5: =SUMIF($D$5:$D$64,$K5,$E$5:$E$64) -> 0 | N5: =IFERROR(M5/$E$3,0) -> 0
K6: Mercado | M6: =SUMIF($D$5:$D$64,$K6,$E$5:$E$64) -> 0 | N6: =IFERROR(M6/$E$3,0) -> 0
K7: Farmácia | M7: =SUMIF($D$5:$D$64,$K7,$E$5:$E$64) -> 0 | N7: =IFERROR(M7/$E$3,0) -> 0
K8: Combustível | M8: =SUMIF($D$5:$D$64,$K8,$E$5:$E$64) -> 0 | N8: =IFERROR(M8/$E$3,0) -> 0
K9: Transporte | M9: =SUMIF($D$5:$D$64,$K9,$E$5:$E$64) -> 0 | N9: =IFERROR(M9/$E$3,0) -> 0
K10: Vestuário | M10: =SUMIF($D$5:$D$64,$K10,$E$5:$E$64) -> 0 | N10: =IFERROR(M10/$E$3,0) -> 0
K11: Eletrônicos | M11: =SUMIF($D$5:$D$64,$K11,$E$5:$E$64) -> 0 | N11: =IFERROR(M11/$E$3,0) -> 0
K12: Casa | M12: =SUMIF($D$5:$D$64,$K12,$E$5:$E$64) -> 0 | N12: =IFERROR(M12/$E$3,0) -> 0
K13: Saúde | M13: =SUMIF($D$5:$D$64,$K13,$E$5:$E$64) -> 0 | N13: =IFERROR(M13/$E$3,0) -> 0
G14: CARTÃO DE CRÉDITO (você preenche) | I14: =SUM(I16:I23) -> 0 | K14: Lazer | M14: =SUMIF($D$5:$D$64,$K14,$E$5:$E$64) -> 0 | N14: =IFERROR(M14/$E$3,0) -> 0
G15: Forma | H15: Categoria | I15: Valor | K15: Serviços | M15: =SUMIF($D$5:$D$64,$K15,$E$5:$E$64) -> 0 | N15: =IFERROR(M15/$E$3,0) -> 0
K16: Outros | M16: =SUMIF($D$5:$D$64,$K16,$E$5:$E$64) -> 0 | N16: =IFERROR(M16/$E$3,0) -> 0
K17: Total | L17: =SUM(L5:L16) -> 0 | M17: =SUM(M5:M16) -> 0 | N17: =IFERROR(M17/$E$3,0) -> 0
K19: CONTAS A PAGAR (faturas)
K20: Descrição | L20: Valor | M20: Vencimento | N20: Pago?
G25: ENTRADAS (você preenche)
G26: Salário
G27: Bônus
G28: Total | I28: =SUM(I26:I27) -> 0
G30: SAÍDAS POR FORMA DE PAGAMENTO
G31: Débito | I31: =SUMIF($C$5:$C$64,$G31,$E$5:$E$64)+SUMIF($G$5:$G$12,$G31,$I$5:$I$12)+SUMIF($G$16:$G$23,$G31,$I$16:$I$23) -> 0
G32: Crédito | I32: =SUMIF($C$5:$C$64,$G32,$E$5:$E$64)+SUMIF($G$5:$G$12,$G32,$I$5:$I$12)+SUMIF($G$16:$G$23,$G32,$I$16:$I$23) -> 0 | K32: INSIGHTS DO MÊS
G33: Pix | I33: =SUMIF($C$5:$C$64,$G33,$E$5:$E$64)+SUMIF($G$5:$G$12,$G33,$I$5:$I$12)+SUMIF($G$16:$G$23,$G33,$I$16:$I$23) -> 0 | K33: Nº de lançamentos | N33: =COUNT($E$5:$E$64) -> 0
G34: Dinheiro | I34: =SUMIF($C$5:$C$64,$G34,$E$5:$E$64)+SUMIF($G$5:$G$12,$G34,$I$5:$I$12)+SUMIF($G$16:$G$23,$G34,$I$16:$I$23) -> 0 | K34: Maior compra | N34: =IF(COUNT($E$5:$E$64)=0,0,MAX($E$5:$E$64)) -> 0
G35: Voucher | I35: =SUMIF($C$5:$C$64,$G35,$E$5:$E$64)+SUMIF($G$5:$G$12,$G35,$I$5:$I$12)+SUMIF($G$16:$G$23,$G35,$I$16:$I$23) -> 0 | K35: Onde foi a maior compra | N35: =IF($E$3=0,"—",INDEX($A$5:$A$64,MATCH(MAX($E$5:$E$64),$E$5:$E$64,0))) -> —
G36: Outros | I36: =SUMIF($C$5:$C$64,$G36,$E$5:$E$64)+SUMIF($G$5:$G$12,$G36,$I$5:$I$12)+SUMIF($G$16:$G$23,$G36,$I$16:$I$23) -> 0 | K36: Categoria campeã | N36: =IF($E$3=0,"—",INDEX($K$5:$K$16,MATCH(MAX($M$5:$M$16),$M$5:$M$16,0))) -> —
G37: Reserva | K37: Ticket médio | N37: =IFERROR(AVERAGE($E$5:$E$64),0) -> 0
G38: Metas | K38: Gasto médio por dia | N38: =IFERROR($E$3/DAY(EOMONTH(DATE(2026,3,1),0)),0) -> 0
G39: Total de saídas | I39: =SUM(I31:I38) -> 0 | K39: % das entradas já gasto | N39: =IFERROR($I$39/$I$28,0) -> 0
G41: INVESTIMENTOS
G42: Reserva
G43: Renda fixa
G44: Total | I44: =SUM(I42:I43) -> 0
G46: SALDO DO MÊS (Entradas − Saídas)
G47: =I28-I39 -> 0

Sheet Abril
A1: Abril · Notinha 2026
A3: GASTOS DO MÊS — lançados pela Notinha | D3: Total do mês | E3: =SUM(E5:E64) -> 0 | G3: FIXOS (você preenche) | I3: =SUM(I5:I12) -> 0 | K3: GASTOS DO MÊS POR CATEGORIA
A4: Nome | B4: Data | C4: Forma | D4: Categoria | E4: Valor | G4: Forma | H4: Categoria | I4: Valor | K4: Categoria | L4: Valor esperado | M4: Valor gasto | N4: %
K5: Alimentação | M5: =SUMIF($D$5:$D$64,$K5,$E$5:$E$64) -> 0 | N5: =IFERROR(M5/$E$3,0) -> 0
K6: Mercado | M6: =SUMIF($D$5:$D$64,$K6,$E$5:$E$64) -> 0 | N6: =IFERROR(M6/$E$3,0) -> 0
K7: Farmácia | M7: =SUMIF($D$5:$D$64,$K7,$E$5:$E$64) -> 0 | N7: =IFERROR(M7/$E$3,0) -> 0
K8: Combustível | M8: =SUMIF($D$5:$D$64,$K8,$E$5:$E$64) -> 0 | N8: =IFERROR(M8/$E$3,0) -> 0
K9: Transporte | M9: =SUMIF($D$5:$D$64,$K9,$E$5:$E$64) -> 0 | N9: =IFERROR(M9/$E$3,0) -> 0
K10: Vestuário | M10: =SUMIF($D$5:$D$64,$K10,$E$5:$E$64) -> 0 | N10: =IFERROR(M10/$E$3,0) -> 0
K11: Eletrônicos | M11: =SUMIF($D$5:$D$64,$K11,$E$5:$E$64) -> 0 | N11: =IFERROR(M11/$E$3,0) -> 0
K12: Casa | M12: =SUMIF($D$5:$D$64,$K12,$E$5:$E$64) -> 0 | N12: =IFERROR(M12/$E$3,0) -> 0
K13: Saúde | M13: =SUMIF($D$5:$D$64,$K13,$E$5:$E$64) -> 0 | N13: =IFERROR(M13/$E$3,0) -> 0
G14: CARTÃO DE CRÉDITO (você preenche) | I14: =SUM(I16:I23) -> 0 | K14: Lazer | M14: =SUMIF($D$5:$D$64,$K14,$E$5:$E$64) -> 0 | N14: =IFERROR(M14/$E$3,0) -> 0
G15: Forma | H15: Categoria | I15: Valor | K15: Serviços | M15: =SUMIF($D$5:$D$64,$K15,$E$5:$E$64) -> 0 | N15: =IFERROR(M15/$E$3,0) -> 0
K16: Outros | M16: =SUMIF($D$5:$D$64,$K16,$E$5:$E$64) -> 0 | N16: =IFERROR(M16/$E$3,0) -> 0
K17: Total | L17: =SUM(L5:L16) -> 0 | M17: =SUM(M5:M16) -> 0 | N17: =IFERROR(M17/$E$3,0) -> 0
K19: CONTAS A PAGAR (faturas)
K20: Descrição | L20: Valor | M20: Vencimento | N20: Pago?
G25: ENTRADAS (você preenche)
G26: Salário
G27: Bônus
G28: Total | I28: =SUM(I26:I27) -> 0
G30: SAÍDAS POR FORMA DE PAGAMENTO
G31: Débito | I31: =SUMIF($C$5:$C$64,$G31,$E$5:$E$64)+SUMIF($G$5:$G$12,$G31,$I$5:$I$12)+SUMIF($G$16:$G$23,$G31,$I$16:$I$23) -> 0
G32: Crédito | I32: =SUMIF($C$5:$C$64,$G32,$E$5:$E$64)+SUMIF($G$5:$G$12,$G32,$I$5:$I$12)+SUMIF($G$16:$G$23,$G32,$I$16:$I$23) -> 0 | K32: INSIGHTS DO MÊS
G33: Pix | I33: =SUMIF($C$5:$C$64,$G33,$E$5:$E$64)+SUMIF($G$5:$G$12,$G33,$I$5:$I$12)+SUMIF($G$16:$G$23,$G33,$I$16:$I$23) -> 0 | K33: Nº de lançamentos | N33: =COUNT($E$5:$E$64) -> 0
G34: Dinheiro | I34: =SUMIF($C$5:$C$64,$G34,$E$5:$E$64)+SUMIF($G$5:$G$12,$G34,$I$5:$I$12)+SUMIF($G$16:$G$23,$G34,$I$16:$I$23) -> 0 | K34: Maior compra | N34: =IF(COUNT($E$5:$E$64)=0,0,MAX($E$5:$E$64)) -> 0
G35: Voucher | I35: =SUMIF($C$5:$C$64,$G35,$E$5:$E$64)+SUMIF($G$5:$G$12,$G35,$I$5:$I$12)+SUMIF($G$16:$G$23,$G35,$I$16:$I$23) -> 0 | K35: Onde foi a maior compra | N35: =IF($E$3=0,"—",INDEX($A$5:$A$64,MATCH(MAX($E$5:$E$64),$E$5:$E$64,0))) -> —
G36: Outros | I36: =SUMIF($C$5:$C$64,$G36,$E$5:$E$64)+SUMIF($G$5:$G$12,$G36,$I$5:$I$12)+SUMIF($G$16:$G$23,$G36,$I$16:$I$23) -> 0 | K36: Categoria campeã | N36: =IF($E$3=0,"—",INDEX($K$5:$K$16,MATCH(MAX($M$5:$M$16),$M$5:$M$16,0))) -> —
G37: Reserva | K37: Ticket médio | N37: =IFERROR(AVERAGE($E$5:$E$64),0) -> 0
G38: Metas | K38: Gasto médio por dia | N38: =IFERROR($E$3/DAY(EOMONTH(DATE(2026,4,1),0)),0) -> 0
G39: Total de saídas | I39: =SUM(I31:I38) -> 0 | K39: % das entradas já gasto | N39: =IFERROR($I$39/$I$28,0) -> 0
G41: INVESTIMENTOS
G42: Reserva
G43: Renda fixa
G44: Total | I44: =SUM(I42:I43) -> 0
G46: SALDO DO MÊS (Entradas − Saídas)
G47: =I28-I39 -> 0

Sheet Maio
A1: Maio · Notinha 2026
A3: GASTOS DO MÊS — lançados pela Notinha | D3: Total do mês | E3: =SUM(E5:E64) -> 0 | G3: FIXOS (você preenche) | I3: =SUM(I5:I12) -> 0 | K3: GASTOS DO MÊS POR CATEGORIA
A4: Nome | B4: Data | C4: Forma | D4: Categoria | E4: Valor | G4: Forma | H4: Categoria | I4: Valor | K4: Categoria | L4: Valor esperado | M4: Valor gasto | N4: %
K5: Alimentação | M5: =SUMIF($D$5:$D$64,$K5,$E$5:$E$64) -> 0 | N5: =IFERROR(M5/$E$3,0) -> 0
K6: Mercado | M6: =SUMIF($D$5:$D$64,$K6,$E$5:$E$64) -> 0 | N6: =IFERROR(M6/$E$3,0) -> 0
K7: Farmácia | M7: =SUMIF($D$5:$D$64,$K7,$E$5:$E$64) -> 0 | N7: =IFERROR(M7/$E$3,0) -> 0
K8: Combustível | M8: =SUMIF($D$5:$D$64,$K8,$E$5:$E$64) -> 0 | N8: =IFERROR(M8/$E$3,0) -> 0
K9: Transporte | M9: =SUMIF($D$5:$D$64,$K9,$E$5:$E$64) -> 0 | N9: =IFERROR(M9/$E$3,0) -> 0
K10: Vestuário | M10: =SUMIF($D$5:$D$64,$K10,$E$5:$E$64) -> 0 | N10: =IFERROR(M10/$E$3,0) -> 0
K11: Eletrônicos | M11: =SUMIF($D$5:$D$64,$K11,$E$5:$E$64) -> 0 | N11: =IFERROR(M11/$E$3,0) -> 0
K12: Casa | M12: =SUMIF($D$5:$D$64,$K12,$E$5:$E$64) -> 0 | N12: =IFERROR(M12/$E$3,0) -> 0
K13: Saúde | M13: =SUMIF($D$5:$D$64,$K13,$E$5:$E$64) -> 0 | N13: =IFERROR(M13/$E$3,0) -> 0
G14: CARTÃO DE CRÉDITO (você preenche) | I14: =SUM(I16:I23) -> 0 | K14: Lazer | M14: =SUMIF($D$5:$D$64,$K14,$E$5:$E$64) -> 0 | N14: =IFERROR(M14/$E$3,0) -> 0
G15: Forma | H15: Categoria | I15: Valor | K15: Serviços | M15: =SUMIF($D$5:$D$64,$K15,$E$5:$E$64) -> 0 | N15: =IFERROR(M15/$E$3,0) -> 0
K16: Outros | M16: =SUMIF($D$5:$D$64,$K16,$E$5:$E$64) -> 0 | N16: =IFERROR(M16/$E$3,0) -> 0
K17: Total | L17: =SUM(L5:L16) -> 0 | M17: =SUM(M5:M16) -> 0 | N17: =IFERROR(M17/$E$3,0) -> 0
K19: CONTAS A PAGAR (faturas)
K20: Descrição | L20: Valor | M20: Vencimento | N20: Pago?
G25: ENTRADAS (você preenche)
G26: Salário
G27: Bônus
G28: Total | I28: =SUM(I26:I27) -> 0
G30: SAÍDAS POR FORMA DE PAGAMENTO
G31: Débito | I31: =SUMIF($C$5:$C$64,$G31,$E$5:$E$64)+SUMIF($G$5:$G$12,$G31,$I$5:$I$12)+SUMIF($G$16:$G$23,$G31,$I$16:$I$23) -> 0
G32: Crédito | I32: =SUMIF($C$5:$C$64,$G32,$E$5:$E$64)+SUMIF($G$5:$G$12,$G32,$I$5:$I$12)+SUMIF($G$16:$G$23,$G32,$I$16:$I$23) -> 0 | K32: INSIGHTS DO MÊS
G33: Pix | I33: =SUMIF($C$5:$C$64,$G33,$E$5:$E$64)+SUMIF($G$5:$G$12,$G33,$I$5:$I$12)+SUMIF($G$16:$G$23,$G33,$I$16:$I$23) -> 0 | K33: Nº de lançamentos | N33: =COUNT($E$5:$E$64) -> 0
G34: Dinheiro | I34: =SUMIF($C$5:$C$64,$G34,$E$5:$E$64)+SUMIF($G$5:$G$12,$G34,$I$5:$I$12)+SUMIF($G$16:$G$23,$G34,$I$16:$I$23) -> 0 | K34: Maior compra | N34: =IF(COUNT($E$5:$E$64)=0,0,MAX($E$5:$E$64)) -> 0
G35: Voucher | I35: =SUMIF($C$5:$C$64,$G35,$E$5:$E$64)+SUMIF($G$5:$G$12,$G35,$I$5:$I$12)+SUMIF($G$16:$G$23,$G35,$I$16:$I$23) -> 0 | K35: Onde foi a maior compra | N35: =IF($E$3=0,"—",INDEX($A$5:$A$64,MATCH(MAX($E$5:$E$64),$E$5:$E$64,0))) -> —
G36: Outros | I36: =SUMIF($C$5:$C$64,$G36,$E$5:$E$64)+SUMIF($G$5:$G$12,$G36,$I$5:$I$12)+SUMIF($G$16:$G$23,$G36,$I$16:$I$23) -> 0 | K36: Categoria campeã | N36: =IF($E$3=0,"—",INDEX($K$5:$K$16,MATCH(MAX($M$5:$M$16),$M$5:$M$16,0))) -> —
G37: Reserva | K37: Ticket médio | N37: =IFERROR(AVERAGE($E$5:$E$64),0) -> 0
G38: Metas | K38: Gasto médio por dia | N38: =IFERROR($E$3/DAY(EOMONTH(DATE(2026,5,1),0)),0) -> 0
G39: Total de saídas | I39: =SUM(I31:I38) -> 0 | K39: % das entradas já gasto | N39: =IFERROR($I$39/$I$28,0) -> 0
G41: INVESTIMENTOS
G42: Reserva
G43: Renda fixa
G44: Total | I44: =SUM(I42:I43) -> 0
G46: SALDO DO MÊS (Entradas − Saídas)
G47: =I28-I39 -> 0

Sheet Junho
A1: Junho · Notinha 2026
A3: GASTOS DO MÊS — lançados pela Notinha | D3: Total do mês | E3: =SUM(E5:E64) -> 0 | G3: FIXOS (você preenche) | I3: =SUM(I5:I12) -> 0 | K3: GASTOS DO MÊS POR CATEGORIA
A4: Nome | B4: Data | C4: Forma | D4: Categoria | E4: Valor | G4: Forma | H4: Categoria | I4: Valor | K4: Categoria | L4: Valor esperado | M4: Valor gasto | N4: %
K5: Alimentação | M5: =SUMIF($D$5:$D$64,$K5,$E$5:$E$64) -> 0 | N5: =IFERROR(M5/$E$3,0) -> 0
K6: Mercado | M6: =SUMIF($D$5:$D$64,$K6,$E$5:$E$64) -> 0 | N6: =IFERROR(M6/$E$3,0) -> 0
K7: Farmácia | M7: =SUMIF($D$5:$D$64,$K7,$E$5:$E$64) -> 0 | N7: =IFERROR(M7/$E$3,0) -> 0
K8: Combustível | M8: =SUMIF($D$5:$D$64,$K8,$E$5:$E$64) -> 0 | N8: =IFERROR(M8/$E$3,0) -> 0
K9: Transporte | M9: =SUMIF($D$5:$D$64,$K9,$E$5:$E$64) -> 0 | N9: =IFERROR(M9/$E$3,0) -> 0
K10: Vestuário | M10: =SUMIF($D$5:$D$64,$K10,$E$5:$E$64) -> 0 | N10: =IFERROR(M10/$E$3,0) -> 0
K11: Eletrônicos | M11: =SUMIF($D$5:$D$64,$K11,$E$5:$E$64) -> 0 | N11: =IFERROR(M11/$E$3,0) -> 0
K12: Casa | M12: =SUMIF($D$5:$D$64,$K12,$E$5:$E$64) -> 0 | N12: =IFERROR(M12/$E$3,0) -> 0
K13: Saúde | M13: =SUMIF($D$5:$D$64,$K13,$E$5:$E$64) -> 0 | N13: =IFERROR(M13/$E$3,0) -> 0
G14: CARTÃO DE CRÉDITO (você preenche) | I14: =SUM(I16:I23) -> 0 | K14: Lazer | M14: =SUMIF($D$5:$D$64,$K14,$E$5:$E$64) -> 0 | N14: =IFERROR(M14/$E$3,0) -> 0
G15: Forma | H15: Categoria | I15: Valor | K15: Serviços | M15: =SUMIF($D$5:$D$64,$K15,$E$5:$E$64) -> 0 | N15: =IFERROR(M15/$E$3,0) -> 0
K16: Outros | M16: =SUMIF($D$5:$D$64,$K16,$E$5:$E$64) -> 0 | N16: =IFERROR(M16/$E$3,0) -> 0
K17: Total | L17: =SUM(L5:L16) -> 0 | M17: =SUM(M5:M16) -> 0 | N17: =IFERROR(M17/$E$3,0) -> 0
K19: CONTAS A PAGAR (faturas)
K20: Descrição | L20: Valor | M20: Vencimento | N20: Pago?
G25: ENTRADAS (você preenche)
G26: Salário
G27: Bônus
G28: Total | I28: =SUM(I26:I27) -> 0
G30: SAÍDAS POR FORMA DE PAGAMENTO
G31: Débito | I31: =SUMIF($C$5:$C$64,$G31,$E$5:$E$64)+SUMIF($G$5:$G$12,$G31,$I$5:$I$12)+SUMIF($G$16:$G$23,$G31,$I$16:$I$23) -> 0
G32: Crédito | I32: =SUMIF($C$5:$C$64,$G32,$E$5:$E$64)+SUMIF($G$5:$G$12,$G32,$I$5:$I$12)+SUMIF($G$16:$G$23,$G32,$I$16:$I$23) -> 0 | K32: INSIGHTS DO MÊS
G33: Pix | I33: =SUMIF($C$5:$C$64,$G33,$E$5:$E$64)+SUMIF($G$5:$G$12,$G33,$I$5:$I$12)+SUMIF($G$16:$G$23,$G33,$I$16:$I$23) -> 0 | K33: Nº de lançamentos | N33: =COUNT($E$5:$E$64) -> 0
G34: Dinheiro | I34: =SUMIF($C$5:$C$64,$G34,$E$5:$E$64)+SUMIF($G$5:$G$12,$G34,$I$5:$I$12)+SUMIF($G$16:$G$23,$G34,$I$16:$I$23) -> 0 | K34: Maior compra | N34: =IF(COUNT($E$5:$E$64)=0,0,MAX($E$5:$E$64)) -> 0
G35: Voucher | I35: =SUMIF($C$5:$C$64,$G35,$E$5:$E$64)+SUMIF($G$5:$G$12,$G35,$I$5:$I$12)+SUMIF($G$16:$G$23,$G35,$I$16:$I$23) -> 0 | K35: Onde foi a maior compra | N35: =IF($E$3=0,"—",INDEX($A$5:$A$64,MATCH(MAX($E$5:$E$64),$E$5:$E$64,0))) -> —
G36: Outros | I36: =SUMIF($C$5:$C$64,$G36,$E$5:$E$64)+SUMIF($G$5:$G$12,$G36,$I$5:$I$12)+SUMIF($G$16:$G$23,$G36,$I$16:$I$23) -> 0 | K36: Categoria campeã | N36: =IF($E$3=0,"—",INDEX($K$5:$K$16,MATCH(MAX($M$5:$M$16),$M$5:$M$16,0))) -> —
G37: Reserva | K37: Ticket médio | N37: =IFERROR(AVERAGE($E$5:$E$64),0) -> 0
G38: Metas | K38: Gasto médio por dia | N38: =IFERROR($E$3/DAY(EOMONTH(DATE(2026,6,1),0)),0) -> 0
G39: Total de saídas | I39: =SUM(I31:I38) -> 0 | K39: % das entradas já gasto | N39: =IFERROR($I$39/$I$28,0) -> 0
G41: INVESTIMENTOS
G42: Reserva
G43: Renda fixa
G44: Total | I44: =SUM(I42:I43) -> 0
G46: SALDO DO MÊS (Entradas − Saídas)
G47: =I28-I39 -> 0

Sheet Julho
A1: Julho · Notinha 2026
A3: GASTOS DO MÊS — lançados pela Notinha | D3: Total do mês | E3: =SUM(E5:E64) -> 0 | G3: FIXOS (você preenche) | I3: =SUM(I5:I12) -> 0 | K3: GASTOS DO MÊS POR CATEGORIA
A4: Nome | B4: Data | C4: Forma | D4: Categoria | E4: Valor | G4: Forma | H4: Categoria | I4: Valor | K4: Categoria | L4: Valor esperado | M4: Valor gasto | N4: %
K5: Alimentação | M5: =SUMIF($D$5:$D$64,$K5,$E$5:$E$64) -> 0 | N5: =IFERROR(M5/$E$3,0) -> 0
K6: Mercado | M6: =SUMIF($D$5:$D$64,$K6,$E$5:$E$64) -> 0 | N6: =IFERROR(M6/$E$3,0) -> 0
K7: Farmácia | M7: =SUMIF($D$5:$D$64,$K7,$E$5:$E$64) -> 0 | N7: =IFERROR(M7/$E$3,0) -> 0
K8: Combustível | M8: =SUMIF($D$5:$D$64,$K8,$E$5:$E$64) -> 0 | N8: =IFERROR(M8/$E$3,0) -> 0
K9: Transporte | M9: =SUMIF($D$5:$D$64,$K9,$E$5:$E$64) -> 0 | N9: =IFERROR(M9/$E$3,0) -> 0
K10: Vestuário | M10: =SUMIF($D$5:$D$64,$K10,$E$5:$E$64) -> 0 | N10: =IFERROR(M10/$E$3,0) -> 0
K11: Eletrônicos | M11: =SUMIF($D$5:$D$64,$K11,$E$5:$E$64) -> 0 | N11: =IFERROR(M11/$E$3,0) -> 0
K12: Casa | M12: =SUMIF($D$5:$D$64,$K12,$E$5:$E$64) -> 0 | N12: =IFERROR(M12/$E$3,0) -> 0
K13: Saúde | M13: =SUMIF($D$5:$D$64,$K13,$E$5:$E$64) -> 0 | N13: =IFERROR(M13/$E$3,0) -> 0
G14: CARTÃO DE CRÉDITO (você preenche) | I14: =SUM(I16:I23) -> 0 | K14: Lazer | M14: =SUMIF($D$5:$D$64,$K14,$E$5:$E$64) -> 0 | N14: =IFERROR(M14/$E$3,0) -> 0
G15: Forma | H15: Categoria | I15: Valor | K15: Serviços | M15: =SUMIF($D$5:$D$64,$K15,$E$5:$E$64) -> 0 | N15: =IFERROR(M15/$E$3,0) -> 0
K16: Outros | M16: =SUMIF($D$5:$D$64,$K16,$E$5:$E$64) -> 0 | N16: =IFERROR(M16/$E$3,0) -> 0
K17: Total | L17: =SUM(L5:L16) -> 0 | M17: =SUM(M5:M16) -> 0 | N17: =IFERROR(M17/$E$3,0) -> 0
K19: CONTAS A PAGAR (faturas)
K20: Descrição | L20: Valor | M20: Vencimento | N20: Pago?
G25: ENTRADAS (você preenche)
G26: Salário
G27: Bônus
G28: Total | I28: =SUM(I26:I27) -> 0
G30: SAÍDAS POR FORMA DE PAGAMENTO
G31: Débito | I31: =SUMIF($C$5:$C$64,$G31,$E$5:$E$64)+SUMIF($G$5:$G$12,$G31,$I$5:$I$12)+SUMIF($G$16:$G$23,$G31,$I$16:$I$23) -> 0
G32: Crédito | I32: =SUMIF($C$5:$C$64,$G32,$E$5:$E$64)+SUMIF($G$5:$G$12,$G32,$I$5:$I$12)+SUMIF($G$16:$G$23,$G32,$I$16:$I$23) -> 0 | K32: INSIGHTS DO MÊS
G33: Pix | I33: =SUMIF($C$5:$C$64,$G33,$E$5:$E$64)+SUMIF($G$5:$G$12,$G33,$I$5:$I$12)+SUMIF($G$16:$G$23,$G33,$I$16:$I$23) -> 0 | K33: Nº de lançamentos | N33: =COUNT($E$5:$E$64) -> 0
G34: Dinheiro | I34: =SUMIF($C$5:$C$64,$G34,$E$5:$E$64)+SUMIF($G$5:$G$12,$G34,$I$5:$I$12)+SUMIF($G$16:$G$23,$G34,$I$16:$I$23) -> 0 | K34: Maior compra | N34: =IF(COUNT($E$5:$E$64)=0,0,MAX($E$5:$E$64)) -> 0
G35: Voucher | I35: =SUMIF($C$5:$C$64,$G35,$E$5:$E$64)+SUMIF($G$5:$G$12,$G35,$I$5:$I$12)+SUMIF($G$16:$G$23,$G35,$I$16:$I$23) -> 0 | K35: Onde foi a maior compra | N35: =IF($E$3=0,"—",INDEX($A$5:$A$64,MATCH(MAX($E$5:$E$64),$E$5:$E$64,0))) -> —
G36: Outros | I36: =SUMIF($C$5:$C$64,$G36,$E$5:$E$64)+SUMIF($G$5:$G$12,$G36,$I$5:$I$12)+SUMIF($G$16:$G$23,$G36,$I$16:$I$23) -> 0 | K36: Categoria campeã | N36: =IF($E$3=0,"—",INDEX($K$5:$K$16,MATCH(MAX($M$5:$M$16),$M$5:$M$16,0))) -> —
G37: Reserva | K37: Ticket médio | N37: =IFERROR(AVERAGE($E$5:$E$64),0) -> 0
G38: Metas | K38: Gasto médio por dia | N38: =IFERROR($E$3/DAY(EOMONTH(DATE(2026,7,1),0)),0) -> 0
G39: Total de saídas | I39: =SUM(I31:I38) -> 0 | K39: % das entradas já gasto | N39: =IFERROR($I$39/$I$28,0) -> 0
G41: INVESTIMENTOS
G42: Reserva
G43: Renda fixa
G44: Total | I44: =SUM(I42:I43) -> 0
G46: SALDO DO MÊS (Entradas − Saídas)
G47: =I28-I39 -> 0

Sheet Agosto
A1: Agosto · Notinha 2026
A3: GASTOS DO MÊS — lançados pela Notinha | D3: Total do mês | E3: =SUM(E5:E64) -> 0 | G3: FIXOS (você preenche) | I3: =SUM(I5:I12) -> 0 | K3: GASTOS DO MÊS POR CATEGORIA
A4: Nome | B4: Data | C4: Forma | D4: Categoria | E4: Valor | G4: Forma | H4: Categoria | I4: Valor | K4: Categoria | L4: Valor esperado | M4: Valor gasto | N4: %
K5: Alimentação | M5: =SUMIF($D$5:$D$64,$K5,$E$5:$E$64) -> 0 | N5: =IFERROR(M5/$E$3,0) -> 0
K6: Mercado | M6: =SUMIF($D$5:$D$64,$K6,$E$5:$E$64) -> 0 | N6: =IFERROR(M6/$E$3,0) -> 0
K7: Farmácia | M7: =SUMIF($D$5:$D$64,$K7,$E$5:$E$64) -> 0 | N7: =IFERROR(M7/$E$3,0) -> 0
K8: Combustível | M8: =SUMIF($D$5:$D$64,$K8,$E$5:$E$64) -> 0 | N8: =IFERROR(M8/$E$3,0) -> 0
K9: Transporte | M9: =SUMIF($D$5:$D$64,$K9,$E$5:$E$64) -> 0 | N9: =IFERROR(M9/$E$3,0) -> 0
K10: Vestuário | M10: =SUMIF($D$5:$D$64,$K10,$E$5:$E$64) -> 0 | N10: =IFERROR(M10/$E$3,0) -> 0
K11: Eletrônicos | M11: =SUMIF($D$5:$D$64,$K11,$E$5:$E$64) -> 0 | N11: =IFERROR(M11/$E$3,0) -> 0
K12: Casa | M12: =SUMIF($D$5:$D$64,$K12,$E$5:$E$64) -> 0 | N12: =IFERROR(M12/$E$3,0) -> 0
K13: Saúde | M13: =SUMIF($D$5:$D$64,$K13,$E$5:$E$64) -> 0 | N13: =IFERROR(M13/$E$3,0) -> 0
G14: CARTÃO DE CRÉDITO (você preenche) | I14: =SUM(I16:I23) -> 0 | K14: Lazer | M14: =SUMIF($D$5:$D$64,$K14,$E$5:$E$64) -> 0 | N14: =IFERROR(M14/$E$3,0) -> 0
G15: Forma | H15: Categoria | I15: Valor | K15: Serviços | M15: =SUMIF($D$5:$D$64,$K15,$E$5:$E$64) -> 0 | N15: =IFERROR(M15/$E$3,0) -> 0
K16: Outros | M16: =SUMIF($D$5:$D$64,$K16,$E$5:$E$64) -> 0 | N16: =IFERROR(M16/$E$3,0) -> 0
K17: Total | L17: =SUM(L5:L16) -> 0 | M17: =SUM(M5:M16) -> 0 | N17: =IFERROR(M17/$E$3,0) -> 0
K19: CONTAS A PAGAR (faturas)
K20: Descrição | L20: Valor | M20: Vencimento | N20: Pago?
G25: ENTRADAS (você preenche)
G26: Salário
G27: Bônus
G28: Total | I28: =SUM(I26:I27) -> 0
G30: SAÍDAS POR FORMA DE PAGAMENTO
G31: Débito | I31: =SUMIF($C$5:$C$64,$G31,$E$5:$E$64)+SUMIF($G$5:$G$12,$G31,$I$5:$I$12)+SUMIF($G$16:$G$23,$G31,$I$16:$I$23) -> 0
G32: Crédito | I32: =SUMIF($C$5:$C$64,$G32,$E$5:$E$64)+SUMIF($G$5:$G$12,$G32,$I$5:$I$12)+SUMIF($G$16:$G$23,$G32,$I$16:$I$23) -> 0 | K32: INSIGHTS DO MÊS
G33: Pix | I33: =SUMIF($C$5:$C$64,$G33,$E$5:$E$64)+SUMIF($G$5:$G$12,$G33,$I$5:$I$12)+SUMIF($G$16:$G$23,$G33,$I$16:$I$23) -> 0 | K33: Nº de lançamentos | N33: =COUNT($E$5:$E$64) -> 0
G34: Dinheiro | I34: =SUMIF($C$5:$C$64,$G34,$E$5:$E$64)+SUMIF($G$5:$G$12,$G34,$I$5:$I$12)+SUMIF($G$16:$G$23,$G34,$I$16:$I$23) -> 0 | K34: Maior compra | N34: =IF(COUNT($E$5:$E$64)=0,0,MAX($E$5:$E$64)) -> 0
G35: Voucher | I35: =SUMIF($C$5:$C$64,$G35,$E$5:$E$64)+SUMIF($G$5:$G$12,$G35,$I$5:$I$12)+SUMIF($G$16:$G$23,$G35,$I$16:$I$23) -> 0 | K35: Onde foi a maior compra | N35: =IF($E$3=0,"—",INDEX($A$5:$A$64,MATCH(MAX($E$5:$E$64),$E$5:$E$64,0))) -> —
G36: Outros | I36: =SUMIF($C$5:$C$64,$G36,$E$5:$E$64)+SUMIF($G$5:$G$12,$G36,$I$5:$I$12)+SUMIF($G$16:$G$23,$G36,$I$16:$I$23) -> 0 | K36: Categoria campeã | N36: =IF($E$3=0,"—",INDEX($K$5:$K$16,MATCH(MAX($M$5:$M$16),$M$5:$M$16,0))) -> —
G37: Reserva | K37: Ticket médio | N37: =IFERROR(AVERAGE($E$5:$E$64),0) -> 0
G38: Metas | K38: Gasto médio por dia | N38: =IFERROR($E$3/DAY(EOMONTH(DATE(2026,8,1),0)),0) -> 0
G39: Total de saídas | I39: =SUM(I31:I38) -> 0 | K39: % das entradas já gasto | N39: =IFERROR($I$39/$I$28,0) -> 0
G41: INVESTIMENTOS
G42: Reserva
G43: Renda fixa
G44: Total | I44: =SUM(I42:I43) -> 0
G46: SALDO DO MÊS (Entradas − Saídas)
G47: =I28-I39 -> 0

Sheet Setembro
A1: Setembro · Notinha 2026
A3: GASTOS DO MÊS — lançados pela Notinha | D3: Total do mês | E3: =SUM(E5:E64) -> 0 | G3: FIXOS (você preenche) | I3: =SUM(I5:I12) -> 0 | K3: GASTOS DO MÊS POR CATEGORIA
A4: Nome | B4: Data | C4: Forma | D4: Categoria | E4: Valor | G4: Forma | H4: Categoria | I4: Valor | K4: Categoria | L4: Valor esperado | M4: Valor gasto | N4: %
K5: Alimentação | M5: =SUMIF($D$5:$D$64,$K5,$E$5:$E$64) -> 0 | N5: =IFERROR(M5/$E$3,0) -> 0
K6: Mercado | M6: =SUMIF($D$5:$D$64,$K6,$E$5:$E$64) -> 0 | N6: =IFERROR(M6/$E$3,0) -> 0
K7: Farmácia | M7: =SUMIF($D$5:$D$64,$K7,$E$5:$E$64) -> 0 | N7: =IFERROR(M7/$E$3,0) -> 0
K8: Combustível | M8: =SUMIF($D$5:$D$64,$K8,$E$5:$E$64) -> 0 | N8: =IFERROR(M8/$E$3,0) -> 0
K9: Transporte | M9: =SUMIF($D$5:$D$64,$K9,$E$5:$E$64) -> 0 | N9: =IFERROR(M9/$E$3,0) -> 0
K10: Vestuário | M10: =SUMIF($D$5:$D$64,$K10,$E$5:$E$64) -> 0 | N10: =IFERROR(M10/$E$3,0) -> 0
K11: Eletrônicos | M11: =SUMIF($D$5:$D$64,$K11,$E$5:$E$64) -> 0 | N11: =IFERROR(M11/$E$3,0) -> 0
K12: Casa | M12: =SUMIF($D$5:$D$64,$K12,$E$5:$E$64) -> 0 | N12: =IFERROR(M12/$E$3,0) -> 0
K13: Saúde | M13: =SUMIF($D$5:$D$64,$K13,$E$5:$E$64) -> 0 | N13: =IFERROR(M13/$E$3,0) -> 0
G14: CARTÃO DE CRÉDITO (você preenche) | I14: =SUM(I16:I23) -> 0 | K14: Lazer | M14: =SUMIF($D$5:$D$64,$K14,$E$5:$E$64) -> 0 | N14: =IFERROR(M14/$E$3,0) -> 0
G15: Forma | H15: Categoria | I15: Valor | K15: Serviços | M15: =SUMIF($D$5:$D$64,$K15,$E$5:$E$64) -> 0 | N15: =IFERROR(M15/$E$3,0) -> 0
K16: Outros | M16: =SUMIF($D$5:$D$64,$K16,$E$5:$E$64) -> 0 | N16: =IFERROR(M16/$E$3,0) -> 0
K17: Total | L17: =SUM(L5:L16) -> 0 | M17: =SUM(M5:M16) -> 0 | N17: =IFERROR(M17/$E$3,0) -> 0
K19: CONTAS A PAGAR (faturas)
K20: Descrição | L20: Valor | M20: Vencimento | N20: Pago?
G25: ENTRADAS (você preenche)
G26: Salário
G27: Bônus
G28: Total | I28: =SUM(I26:I27) -> 0
G30: SAÍDAS POR FORMA DE PAGAMENTO
G31: Débito | I31: =SUMIF($C$5:$C$64,$G31,$E$5:$E$64)+SUMIF($G$5:$G$12,$G31,$I$5:$I$12)+SUMIF($G$16:$G$23,$G31,$I$16:$I$23) -> 0
G32: Crédito | I32: =SUMIF($C$5:$C$64,$G32,$E$5:$E$64)+SUMIF($G$5:$G$12,$G32,$I$5:$I$12)+SUMIF($G$16:$G$23,$G32,$I$16:$I$23) -> 0 | K32: INSIGHTS DO MÊS
G33: Pix | I33: =SUMIF($C$5:$C$64,$G33,$E$5:$E$64)+SUMIF($G$5:$G$12,$G33,$I$5:$I$12)+SUMIF($G$16:$G$23,$G33,$I$16:$I$23) -> 0 | K33: Nº de lançamentos | N33: =COUNT($E$5:$E$64) -> 0
G34: Dinheiro | I34: =SUMIF($C$5:$C$64,$G34,$E$5:$E$64)+SUMIF($G$5:$G$12,$G34,$I$5:$I$12)+SUMIF($G$16:$G$23,$G34,$I$16:$I$23) -> 0 | K34: Maior compra | N34: =IF(COUNT($E$5:$E$64)=0,0,MAX($E$5:$E$64)) -> 0
G35: Voucher | I35: =SUMIF($C$5:$C$64,$G35,$E$5:$E$64)+SUMIF($G$5:$G$12,$G35,$I$5:$I$12)+SUMIF($G$16:$G$23,$G35,$I$16:$I$23) -> 0 | K35: Onde foi a maior compra | N35: =IF($E$3=0,"—",INDEX($A$5:$A$64,MATCH(MAX($E$5:$E$64),$E$5:$E$64,0))) -> —
G36: Outros | I36: =SUMIF($C$5:$C$64,$G36,$E$5:$E$64)+SUMIF($G$5:$G$12,$G36,$I$5:$I$12)+SUMIF($G$16:$G$23,$G36,$I$16:$I$23) -> 0 | K36: Categoria campeã | N36: =IF($E$3=0,"—",INDEX($K$5:$K$16,MATCH(MAX($M$5:$M$16),$M$5:$M$16,0))) -> —
G37: Reserva | K37: Ticket médio | N37: =IFERROR(AVERAGE($E$5:$E$64),0) -> 0
G38: Metas | K38: Gasto médio por dia | N38: =IFERROR($E$3/DAY(EOMONTH(DATE(2026,9,1),0)),0) -> 0
G39: Total de saídas | I39: =SUM(I31:I38) -> 0 | K39: % das entradas já gasto | N39: =IFERROR($I$39/$I$28,0) -> 0
G41: INVESTIMENTOS
G42: Reserva
G43: Renda fixa
G44: Total | I44: =SUM(I42:I43) -> 0
G46: SALDO DO MÊS (Entradas − Saídas)
G47: =I28-I39 -> 0

Sheet Outubro
A1: Outubro · Notinha 2026
A3: GASTOS DO MÊS — lançados pela Notinha | D3: Total do mês | E3: =SUM(E5:E64) -> 0 | G3: FIXOS (você preenche) | I3: =SUM(I5:I12) -> 0 | K3: GASTOS DO MÊS POR CATEGORIA
A4: Nome | B4: Data | C4: Forma | D4: Categoria | E4: Valor | G4: Forma | H4: Categoria | I4: Valor | K4: Categoria | L4: Valor esperado | M4: Valor gasto | N4: %
K5: Alimentação | M5: =SUMIF($D$5:$D$64,$K5,$E$5:$E$64) -> 0 | N5: =IFERROR(M5/$E$3,0) -> 0
K6: Mercado | M6: =SUMIF($D$5:$D$64,$K6,$E$5:$E$64) -> 0 | N6: =IFERROR(M6/$E$3,0) -> 0
K7: Farmácia | M7: =SUMIF($D$5:$D$64,$K7,$E$5:$E$64) -> 0 | N7: =IFERROR(M7/$E$3,0) -> 0
K8: Combustível | M8: =SUMIF($D$5:$D$64,$K8,$E$5:$E$64) -> 0 | N8: =IFERROR(M8/$E$3,0) -> 0
K9: Transporte | M9: =SUMIF($D$5:$D$64,$K9,$E$5:$E$64) -> 0 | N9: =IFERROR(M9/$E$3,0) -> 0
K10: Vestuário | M10: =SUMIF($D$5:$D$64,$K10,$E$5:$E$64) -> 0 | N10: =IFERROR(M10/$E$3,0) -> 0
K11: Eletrônicos | M11: =SUMIF($D$5:$D$64,$K11,$E$5:$E$64) -> 0 | N11: =IFERROR(M11/$E$3,0) -> 0
K12: Casa | M12: =SUMIF($D$5:$D$64,$K12,$E$5:$E$64) -> 0 | N12: =IFERROR(M12/$E$3,0) -> 0
K13: Saúde | M13: =SUMIF($D$5:$D$64,$K13,$E$5:$E$64) -> 0 | N13: =IFERROR(M13/$E$3,0) -> 0
G14: CARTÃO DE CRÉDITO (você preenche) | I14: =SUM(I16:I23) -> 0 | K14: Lazer | M14: =SUMIF($D$5:$D$64,$K14,$E$5:$E$64) -> 0 | N14: =IFERROR(M14/$E$3,0) -> 0
G15: Forma | H15: Categoria | I15: Valor | K15: Serviços | M15: =SUMIF($D$5:$D$64,$K15,$E$5:$E$64) -> 0 | N15: =IFERROR(M15/$E$3,0) -> 0
K16: Outros | M16: =SUMIF($D$5:$D$64,$K16,$E$5:$E$64) -> 0 | N16: =IFERROR(M16/$E$3,0) -> 0
K17: Total | L17: =SUM(L5:L16) -> 0 | M17: =SUM(M5:M16) -> 0 | N17: =IFERROR(M17/$E$3,0) -> 0
K19: CONTAS A PAGAR (faturas)
K20: Descrição | L20: Valor | M20: Vencimento | N20: Pago?
G25: ENTRADAS (você preenche)
G26: Salário
G27: Bônus
G28: Total | I28: =SUM(I26:I27) -> 0
G30: SAÍDAS POR FORMA DE PAGAMENTO
G31: Débito | I31: =SUMIF($C$5:$C$64,$G31,$E$5:$E$64)+SUMIF($G$5:$G$12,$G31,$I$5:$I$12)+SUMIF($G$16:$G$23,$G31,$I$16:$I$23) -> 0
G32: Crédito | I32: =SUMIF($C$5:$C$64,$G32,$E$5:$E$64)+SUMIF($G$5:$G$12,$G32,$I$5:$I$12)+SUMIF($G$16:$G$23,$G32,$I$16:$I$23) -> 0 | K32: INSIGHTS DO MÊS
G33: Pix | I33: =SUMIF($C$5:$C$64,$G33,$E$5:$E$64)+SUMIF($G$5:$G$12,$G33,$I$5:$I$12)+SUMIF($G$16:$G$23,$G33,$I$16:$I$23) -> 0 | K33: Nº de lançamentos | N33: =COUNT($E$5:$E$64) -> 0
G34: Dinheiro | I34: =SUMIF($C$5:$C$64,$G34,$E$5:$E$64)+SUMIF($G$5:$G$12,$G34,$I$5:$I$12)+SUMIF($G$16:$G$23,$G34,$I$16:$I$23) -> 0 | K34: Maior compra | N34: =IF(COUNT($E$5:$E$64)=0,0,MAX($E$5:$E$64)) -> 0
G35: Voucher | I35: =SUMIF($C$5:$C$64,$G35,$E$5:$E$64)+SUMIF($G$5:$G$12,$G35,$I$5:$I$12)+SUMIF($G$16:$G$23,$G35,$I$16:$I$23) -> 0 | K35: Onde foi a maior compra | N35: =IF($E$3=0,"—",INDEX($A$5:$A$64,MATCH(MAX($E$5:$E$64),$E$5:$E$64,0))) -> —
G36: Outros | I36: =SUMIF($C$5:$C$64,$G36,$E$5:$E$64)+SUMIF($G$5:$G$12,$G36,$I$5:$I$12)+SUMIF($G$16:$G$23,$G36,$I$16:$I$23) -> 0 | K36: Categoria campeã | N36: =IF($E$3=0,"—",INDEX($K$5:$K$16,MATCH(MAX($M$5:$M$16),$M$5:$M$16,0))) -> —
G37: Reserva | K37: Ticket médio | N37: =IFERROR(AVERAGE($E$5:$E$64),0) -> 0
G38: Metas | K38: Gasto médio por dia | N38: =IFERROR($E$3/DAY(EOMONTH(DATE(2026,10,1),0)),0) -> 0
G39: Total de saídas | I39: =SUM(I31:I38) -> 0 | K39: % das entradas já gasto | N39: =IFERROR($I$39/$I$28,0) -> 0
G41: INVESTIMENTOS
G42: Reserva
G43: Renda fixa
G44: Total | I44: =SUM(I42:I43) -> 0
G46: SALDO DO MÊS (Entradas − Saídas)
G47: =I28-I39 -> 0

Sheet Novembro
A1: Novembro · Notinha 2026
A3: GASTOS DO MÊS — lançados pela Notinha | D3: Total do mês | E3: =SUM(E5:E64) -> 0 | G3: FIXOS (você preenche) | I3: =SUM(I5:I12) -> 0 | K3: GASTOS DO MÊS POR CATEGORIA
A4: Nome | B4: Data | C4: Forma | D4: Categoria | E4: Valor | G4: Forma | H4: Categoria | I4: Valor | K4: Categoria | L4: Valor esperado | M4: Valor gasto | N4: %
K5: Alimentação | M5: =SUMIF($D$5:$D$64,$K5,$E$5:$E$64) -> 0 | N5: =IFERROR(M5/$E$3,0) -> 0
K6: Mercado | M6: =SUMIF($D$5:$D$64,$K6,$E$5:$E$64) -> 0 | N6: =IFERROR(M6/$E$3,0) -> 0
K7: Farmácia | M7: =SUMIF($D$5:$D$64,$K7,$E$5:$E$64) -> 0 | N7: =IFERROR(M7/$E$3,0) -> 0
K8: Combustível | M8: =SUMIF($D$5:$D$64,$K8,$E$5:$E$64) -> 0 | N8: =IFERROR(M8/$E$3,0) -> 0
K9: Transporte | M9: =SUMIF($D$5:$D$64,$K9,$E$5:$E$64) -> 0 | N9: =IFERROR(M9/$E$3,0) -> 0
K10: Vestuário | M10: =SUMIF($D$5:$D$64,$K10,$E$5:$E$64) -> 0 | N10: =IFERROR(M10/$E$3,0) -> 0
K11: Eletrônicos | M11: =SUMIF($D$5:$D$64,$K11,$E$5:$E$64) -> 0 | N11: =IFERROR(M11/$E$3,0) -> 0
K12: Casa | M12: =SUMIF($D$5:$D$64,$K12,$E$5:$E$64) -> 0 | N12: =IFERROR(M12/$E$3,0) -> 0
K13: Saúde | M13: =SUMIF($D$5:$D$64,$K13,$E$5:$E$64) -> 0 | N13: =IFERROR(M13/$E$3,0) -> 0
G14: CARTÃO DE CRÉDITO (você preenche) | I14: =SUM(I16:I23) -> 0 | K14: Lazer | M14: =SUMIF($D$5:$D$64,$K14,$E$5:$E$64) -> 0 | N14: =IFERROR(M14/$E$3,0) -> 0
G15: Forma | H15: Categoria | I15: Valor | K15: Serviços | M15: =SUMIF($D$5:$D$64,$K15,$E$5:$E$64) -> 0 | N15: =IFERROR(M15/$E$3,0) -> 0
K16: Outros | M16: =SUMIF($D$5:$D$64,$K16,$E$5:$E$64) -> 0 | N16: =IFERROR(M16/$E$3,0) -> 0
K17: Total | L17: =SUM(L5:L16) -> 0 | M17: =SUM(M5:M16) -> 0 | N17: =IFERROR(M17/$E$3,0) -> 0
K19: CONTAS A PAGAR (faturas)
K20: Descrição | L20: Valor | M20: Vencimento | N20: Pago?
G25: ENTRADAS (você preenche)
G26: Salário
G27: Bônus
G28: Total | I28: =SUM(I26:I27) -> 0
G30: SAÍDAS POR FORMA DE PAGAMENTO
G31: Débito | I31: =SUMIF($C$5:$C$64,$G31,$E$5:$E$64)+SUMIF($G$5:$G$12,$G31,$I$5:$I$12)+SUMIF($G$16:$G$23,$G31,$I$16:$I$23) -> 0
G32: Crédito | I32: =SUMIF($C$5:$C$64,$G32,$E$5:$E$64)+SUMIF($G$5:$G$12,$G32,$I$5:$I$12)+SUMIF($G$16:$G$23,$G32,$I$16:$I$23) -> 0 | K32: INSIGHTS DO MÊS
G33: Pix | I33: =SUMIF($C$5:$C$64,$G33,$E$5:$E$64)+SUMIF($G$5:$G$12,$G33,$I$5:$I$12)+SUMIF($G$16:$G$23,$G33,$I$16:$I$23) -> 0 | K33: Nº de lançamentos | N33: =COUNT($E$5:$E$64) -> 0
G34: Dinheiro | I34: =SUMIF($C$5:$C$64,$G34,$E$5:$E$64)+SUMIF($G$5:$G$12,$G34,$I$5:$I$12)+SUMIF($G$16:$G$23,$G34,$I$16:$I$23) -> 0 | K34: Maior compra | N34: =IF(COUNT($E$5:$E$64)=0,0,MAX($E$5:$E$64)) -> 0
G35: Voucher | I35: =SUMIF($C$5:$C$64,$G35,$E$5:$E$64)+SUMIF($G$5:$G$12,$G35,$I$5:$I$12)+SUMIF($G$16:$G$23,$G35,$I$16:$I$23) -> 0 | K35: Onde foi a maior compra | N35: =IF($E$3=0,"—",INDEX($A$5:$A$64,MATCH(MAX($E$5:$E$64),$E$5:$E$64,0))) -> —
G36: Outros | I36: =SUMIF($C$5:$C$64,$G36,$E$5:$E$64)+SUMIF($G$5:$G$12,$G36,$I$5:$I$12)+SUMIF($G$16:$G$23,$G36,$I$16:$I$23) -> 0 | K36: Categoria campeã | N36: =IF($E$3=0,"—",INDEX($K$5:$K$16,MATCH(MAX($M$5:$M$16),$M$5:$M$16,0))) -> —
G37: Reserva | K37: Ticket médio | N37: =IFERROR(AVERAGE($E$5:$E$64),0) -> 0
G38: Metas | K38: Gasto médio por dia | N38: =IFERROR($E$3/DAY(EOMONTH(DATE(2026,11,1),0)),0) -> 0
G39: Total de saídas | I39: =SUM(I31:I38) -> 0 | K39: % das entradas já gasto | N39: =IFERROR($I$39/$I$28,0) -> 0
G41: INVESTIMENTOS
G42: Reserva
G43: Renda fixa
G44: Total | I44: =SUM(I42:I43) -> 0
G46: SALDO DO MÊS (Entradas − Saídas)
G47: =I28-I39 -> 0

Sheet Dezembro
A1: Dezembro · Notinha 2026
A3: GASTOS DO MÊS — lançados pela Notinha | D3: Total do mês | E3: =SUM(E5:E64) -> 0 | G3: FIXOS (você preenche) | I3: =SUM(I5:I12) -> 0 | K3: GASTOS DO MÊS POR CATEGORIA
A4: Nome | B4: Data | C4: Forma | D4: Categoria | E4: Valor | G4: Forma | H4: Categoria | I4: Valor | K4: Categoria | L4: Valor esperado | M4: Valor gasto | N4: %
K5: Alimentação | M5: =SUMIF($D$5:$D$64,$K5,$E$5:$E$64) -> 0 | N5: =IFERROR(M5/$E$3,0) -> 0
K6: Mercado | M6: =SUMIF($D$5:$D$64,$K6,$E$5:$E$64) -> 0 | N6: =IFERROR(M6/$E$3,0) -> 0
K7: Farmácia | M7: =SUMIF($D$5:$D$64,$K7,$E$5:$E$64) -> 0 | N7: =IFERROR(M7/$E$3,0) -> 0
K8: Combustível | M8: =SUMIF($D$5:$D$64,$K8,$E$5:$E$64) -> 0 | N8: =IFERROR(M8/$E$3,0) -> 0
K9: Transporte | M9: =SUMIF($D$5:$D$64,$K9,$E$5:$E$64) -> 0 | N9: =IFERROR(M9/$E$3,0) -> 0
K10: Vestuário | M10: =SUMIF($D$5:$D$64,$K10,$E$5:$E$64) -> 0 | N10: =IFERROR(M10/$E$3,0) -> 0
K11: Eletrônicos | M11: =SUMIF($D$5:$D$64,$K11,$E$5:$E$64) -> 0 | N11: =IFERROR(M11/$E$3,0) -> 0
K12: Casa | M12: =SUMIF($D$5:$D$64,$K12,$E$5:$E$64) -> 0 | N12: =IFERROR(M12/$E$3,0) -> 0
K13: Saúde | M13: =SUMIF($D$5:$D$64,$K13,$E$5:$E$64) -> 0 | N13: =IFERROR(M13/$E$3,0) -> 0
G14: CARTÃO DE CRÉDITO (você preenche) | I14: =SUM(I16:I23) -> 0 | K14: Lazer | M14: =SUMIF($D$5:$D$64,$K14,$E$5:$E$64) -> 0 | N14: =IFERROR(M14/$E$3,0) -> 0
G15: Forma | H15: Categoria | I15: Valor | K15: Serviços | M15: =SUMIF($D$5:$D$64,$K15,$E$5:$E$64) -> 0 | N15: =IFERROR(M15/$E$3,0) -> 0
K16: Outros | M16: =SUMIF($D$5:$D$64,$K16,$E$5:$E$64) -> 0 | N16: =IFERROR(M16/$E$3,0) -> 0
K17: Total | L17: =SUM(L5:L16) -> 0 | M17: =SUM(M5:M16) -> 0 | N17: =IFERROR(M17/$E$3,0) -> 0
K19: CONTAS A PAGAR (faturas)
K20: Descrição | L20: Valor | M20: Vencimento | N20: Pago?
G25: ENTRADAS (você preenche)
G26: Salário
G27: Bônus
G28: Total | I28: =SUM(I26:I27) -> 0
G30: SAÍDAS POR FORMA DE PAGAMENTO
G31: Débito | I31: =SUMIF($C$5:$C$64,$G31,$E$5:$E$64)+SUMIF($G$5:$G$12,$G31,$I$5:$I$12)+SUMIF($G$16:$G$23,$G31,$I$16:$I$23) -> 0
G32: Crédito | I32: =SUMIF($C$5:$C$64,$G32,$E$5:$E$64)+SUMIF($G$5:$G$12,$G32,$I$5:$I$12)+SUMIF($G$16:$G$23,$G32,$I$16:$I$23) -> 0 | K32: INSIGHTS DO MÊS
G33: Pix | I33: =SUMIF($C$5:$C$64,$G33,$E$5:$E$64)+SUMIF($G$5:$G$12,$G33,$I$5:$I$12)+SUMIF($G$16:$G$23,$G33,$I$16:$I$23) -> 0 | K33: Nº de lançamentos | N33: =COUNT($E$5:$E$64) -> 0
G34: Dinheiro | I34: =SUMIF($C$5:$C$64,$G34,$E$5:$E$64)+SUMIF($G$5:$G$12,$G34,$I$5:$I$12)+SUMIF($G$16:$G$23,$G34,$I$16:$I$23) -> 0 | K34: Maior compra | N34: =IF(COUNT($E$5:$E$64)=0,0,MAX($E$5:$E$64)) -> 0
G35: Voucher | I35: =SUMIF($C$5:$C$64,$G35,$E$5:$E$64)+SUMIF($G$5:$G$12,$G35,$I$5:$I$12)+SUMIF($G$16:$G$23,$G35,$I$16:$I$23) -> 0 | K35: Onde foi a maior compra | N35: =IF($E$3=0,"—",INDEX($A$5:$A$64,MATCH(MAX($E$5:$E$64),$E$5:$E$64,0))) -> —
G36: Outros | I36: =SUMIF($C$5:$C$64,$G36,$E$5:$E$64)+SUMIF($G$5:$G$12,$G36,$I$5:$I$12)+SUMIF($G$16:$G$23,$G36,$I$16:$I$23) -> 0 | K36: Categoria campeã | N36: =IF($E$3=0,"—",INDEX($K$5:$K$16,MATCH(MAX($M$5:$M$16),$M$5:$M$16,0))) -> —
G37: Reserva | K37: Ticket médio | N37: =IFERROR(AVERAGE($E$5:$E$64),0) -> 0
G38: Metas | K38: Gasto médio por dia | N38: =IFERROR($E$3/DAY(EOMONTH(DATE(2026,12,1),0)),0) -> 0
G39: Total de saídas | I39: =SUM(I31:I38) -> 0 | K39: % das entradas já gasto | N39: =IFERROR($I$39/$I$28,0) -> 0
G41: INVESTIMENTOS
G42: Reserva
G43: Renda fixa
G44: Total | I44: =SUM(I42:I43) -> 0
G46: SALDO DO MÊS (Entradas − Saídas)
G47: =I28-I39 -> 0

Sheet Visão Anual
A1: Visão Anual · Notinha 2026
A3: RESUMO MENSAL
A4: Mês | B4: Total Entradas | C4: Total Saídas | D4: Saldo
A5: Janeiro | B5: =Janeiro!$I$28 -> 0 | C5: =Janeiro!$I$39 -> 649.6 | D5: =Janeiro!$I$28-Janeiro!$I$39 -> -649.6
A6: Fevereiro | B6: =Fevereiro!$I$28 -> 0 | C6: =Fevereiro!$I$39 -> 0 | D6: =Fevereiro!$I$28-Fevereiro!$I$39 -> 0
A7: Março | B7: =Março!$I$28 -> 0 | C7: =Março!$I$39 -> 0 | D7: =Março!$I$28-Março!$I$39 -> 0
A8: Abril | B8: =Abril!$I$28 -> 0 | C8: =Abril!$I$39 -> 0 | D8: =Abril!$I$28-Abril!$I$39 -> 0
A9: Maio | B9: =Maio!$I$28 -> 0 | C9: =Maio!$I$39 -> 0 | D9: =Maio!$I$28-Maio!$I$39 -> 0
A10: Junho | B10: =Junho!$I$28 -> 0 | C10: =Junho!$I$39 -> 0 | D10: =Junho!$I$28-Junho!$I$39 -> 0
A11: Julho | B11: =Julho!$I$28 -> 0 | C11: =Julho!$I$39 -> 0 | D11: =Julho!$I$28-Julho!$I$39 -> 0
A12: Agosto | B12: =Agosto!$I$28 -> 0 | C12: =Agosto!$I$39 -> 0 | D12: =Agosto!$I$28-Agosto!$I$39 -> 0
A13: Setembro | B13: =Setembro!$I$28 -> 0 | C13: =Setembro!$I$39 -> 0 | D13: =Setembro!$I$28-Setembro!$I$39 -> 0
A14: Outubro | B14: =Outubro!$I$28 -> 0 | C14: =Outubro!$I$39 -> 0 | D14: =Outubro!$I$28-Outubro!$I$39 -> 0
A15: Novembro | B15: =Novembro!$I$28 -> 0 | C15: =Novembro!$I$39 -> 0 | D15: =Novembro!$I$28-Novembro!$I$39 -> 0
A16: Dezembro | B16: =Dezembro!$I$28 -> 0 | C16: =Dezembro!$I$39 -> 0 | D16: =Dezembro!$I$28-Dezembro!$I$39 -> 0
A17: TOTAL DO ANO | B17: =SUM(B5:B16) -> 0 | C17: =SUM(C5:C16) -> 649.6 | D17: =SUM(D5:D16) -> -649.6
A20: GASTOS POR CATEGORIA × MÊS
A21: Categoria | B21: Jan | C21: Fev | D21: Mar | E21: Abr | F21: Mai | G21: Jun | H21: Jul | I21: Ago | J21: Set | K21: Out | L21: Nov | M21: Dez | N21: Total
A22: Alimentação | B22: =Janeiro!$M$5 -> 56.9 | C22: =Fevereiro!$M$5 -> 0 | D22: =Março!$M$5 -> 0 | E22: =Abril!$M$5 -> 0 | F22: =Maio!$M$5 -> 0 | G22: =Junho!$M$5 -> 0 | H22: =Julho!$M$5 -> 0 | I22: =Agosto!$M$5 -> 0 | J22: =Setembro!$M$5 -> 0 | K22: =Outubro!$M$5 -> 0 | L22: =Novembro!$M$5 -> 0 | M22: =Dezembro!$M$5 -> 0 | N22: =SUM(B22:M22) -> 56.9
A23: Mercado | B23: =Janeiro!$M$6 -> 312.45 | C23: =Fevereiro!$M$6 -> 0 | D23: =Março!$M$6 -> 0 | E23: =Abril!$M$6 -> 0 | F23: =Maio!$M$6 -> 0 | G23: =Junho!$M$6 -> 0 | H23: =Julho!$M$6 -> 0 | I23: =Agosto!$M$6 -> 0 | J23: =Setembro!$M$6 -> 0 | K23: =Outubro!$M$6 -> 0 | L23: =Novembro!$M$6 -> 0 | M23: =Dezembro!$M$6 -> 0 | N23: =SUM(B23:M23) -> 312.45
A24: Farmácia | B24: =Janeiro!$M$7 -> 74.2 | C24: =Fevereiro!$M$7 -> 0 | D24: =Março!$M$7 -> 0 | E24: =Abril!$M$7 -> 0 | F24: =Maio!$M$7 -> 0 | G24: =Junho!$M$7 -> 0 | H24: =Julho!$M$7 -> 0 | I24: =Agosto!$M$7 -> 0 | J24: =Setembro!$M$7 -> 0 | K24: =Outubro!$M$7 -> 0 | L24: =Novembro!$M$7 -> 0 | M24: =Dezembro!$M$7 -> 0 | N24: =SUM(B24:M24) -> 74.2
A25: Combustível | B25: =Janeiro!$M$8 -> 0 | C25: =Fevereiro!$M$8 -> 0 | D25: =Março!$M$8 -> 0 | E25: =Abril!$M$8 -> 0 | F25: =Maio!$M$8 -> 0 | G25: =Junho!$M$8 -> 0 | H25: =Julho!$M$8 -> 0 | I25: =Agosto!$M$8 -> 0 | J25: =Setembro!$M$8 -> 0 | K25: =Outubro!$M$8 -> 0 | L25: =Novembro!$M$8 -> 0 | M25: =Dezembro!$M$8 -> 0 | N25: =SUM(B25:M25) -> 0
A26: Transporte | B26: =Janeiro!$M$9 -> 18.75 | C26: =Fevereiro!$M$9 -> 0 | D26: =Março!$M$9 -> 0 | E26: =Abril!$M$9 -> 0 | F26: =Maio!$M$9 -> 0 | G26: =Junho!$M$9 -> 0 | H26: =Julho!$M$9 -> 0 | I26: =Agosto!$M$9 -> 0 | J26: =Setembro!$M$9 -> 0 | K26: =Outubro!$M$9 -> 0 | L26: =Novembro!$M$9 -> 0 | M26: =Dezembro!$M$9 -> 0 | N26: =SUM(B26:M26) -> 18.75
A27: Vestuário | B27: =Janeiro!$M$10 -> 0 | C27: =Fevereiro!$M$10 -> 0 | D27: =Março!$M$10 -> 0 | E27: =Abril!$M$10 -> 0 | F27: =Maio!$M$10 -> 0 | G27: =Junho!$M$10 -> 0 | H27: =Julho!$M$10 -> 0 | I27: =Agosto!$M$10 -> 0 | J27: =Setembro!$M$10 -> 0 | K27: =Outubro!$M$10 -> 0 | L27: =Novembro!$M$10 -> 0 | M27: =Dezembro!$M$10 -> 0 | N27: =SUM(B27:M27) -> 0
A28: Eletrônicos | B28: =Janeiro!$M$11 -> 0 | C28: =Fevereiro!$M$11 -> 0 | D28: =Março!$M$11 -> 0 | E28: =Abril!$M$11 -> 0 | F28: =Maio!$M$11 -> 0 | G28: =Junho!$M$11 -> 0 | H28: =Julho!$M$11 -> 0 | I28: =Agosto!$M$11 -> 0 | J28: =Setembro!$M$11 -> 0 | K28: =Outubro!$M$11 -> 0 | L28: =Novembro!$M$11 -> 0 | M28: =Dezembro!$M$11 -> 0 | N28: =SUM(B28:M28) -> 0
A29: Casa | B29: =Janeiro!$M$12 -> 187.3 | C29: =Fevereiro!$M$12 -> 0 | D29: =Março!$M$12 -> 0 | E29: =Abril!$M$12 -> 0 | F29: =Maio!$M$12 -> 0 | G29: =Junho!$M$12 -> 0 | H29: =Julho!$M$12 -> 0 | I29: =Agosto!$M$12 -> 0 | J29: =Setembro!$M$12 -> 0 | K29: =Outubro!$M$12 -> 0 | L29: =Novembro!$M$12 -> 0 | M29: =Dezembro!$M$12 -> 0 | N29: =SUM(B29:M29) -> 187.3
A30: Saúde | B30: =Janeiro!$M$13 -> 0 | C30: =Fevereiro!$M$13 -> 0 | D30: =Março!$M$13 -> 0 | E30: =Abril!$M$13 -> 0 | F30: =Maio!$M$13 -> 0 | G30: =Junho!$M$13 -> 0 | H30: =Julho!$M$13 -> 0 | I30: =Agosto!$M$13 -> 0 | J30: =Setembro!$M$13 -> 0 | K30: =Outubro!$M$13 -> 0 | L30: =Novembro!$M$13 -> 0 | M30: =Dezembro!$M$13 -> 0 | N30: =SUM(B30:M30) -> 0
A31: Lazer | B31: =Janeiro!$M$14 -> 0 | C31: =Fevereiro!$M$14 -> 0 | D31: =Março!$M$14 -> 0 | E31: =Abril!$M$14 -> 0 | F31: =Maio!$M$14 -> 0 | G31: =Junho!$M$14 -> 0 | H31: =Julho!$M$14 -> 0 | I31: =Agosto!$M$14 -> 0 | J31: =Setembro!$M$14 -> 0 | K31: =Outubro!$M$14 -> 0 | L31: =Novembro!$M$14 -> 0 | M31: =Dezembro!$M$14 -> 0 | N31: =SUM(B31:M31) -> 0
A32: Serviços | B32: =Janeiro!$M$15 -> 0 | C32: =Fevereiro!$M$15 -> 0 | D32: =Março!$M$15 -> 0 | E32: =Abril!$M$15 -> 0 | F32: =Maio!$M$15 -> 0 | G32: =Junho!$M$15 -> 0 | H32: =Julho!$M$15 -> 0 | I32: =Agosto!$M$15 -> 0 | J32: =Setembro!$M$15 -> 0 | K32: =Outubro!$M$15 -> 0 | L32: =Novembro!$M$15 -> 0 | M32: =Dezembro!$M$15 -> 0 | N32: =SUM(B32:M32) -> 0
A33: Outros | B33: =Janeiro!$M$16 -> 0 | C33: =Fevereiro!$M$16 -> 0 | D33: =Março!$M$16 -> 0 | E33: =Abril!$M$16 -> 0 | F33: =Maio!$M$16 -> 0 | G33: =Junho!$M$16 -> 0 | H33: =Julho!$M$16 -> 0 | I33: =Agosto!$M$16 -> 0 | J33: =Setembro!$M$16 -> 0 | K33: =Outubro!$M$16 -> 0 | L33: =Novembro!$M$16 -> 0 | M33: =Dezembro!$M$16 -> 0 | N33: =SUM(B33:M33) -> 0
A34: Total | B34: =SUM(B22:B33) -> 649.6 | C34: =SUM(C22:C33) -> 0 | D34: =SUM(D22:D33) -> 0 | E34: =SUM(E22:E33) -> 0 | F34: =SUM(F22:F33) -> 0 | G34: =SUM(G22:G33) -> 0 | H34: =SUM(H22:H33) -> 0 | I34: =SUM(I22:I33) -> 0 | ... N34: =SUM(N22:N33) -> 649.6
A37: TOP PRODUTOS MAIS COMPRADOS | E37: MAIORES VARIAÇÕES DE PREÇO
A38: Produto | B38: Vezes | C38: Gasto total | E38: Produto | F38: Antes | G38: Agora | H38: Variação
A51: INSIGHTS DO ANO
A52: Mês com maior gasto | D52: =IF(MAX(C5:C16)=0,"—",INDEX(A5:A16,MATCH(MAX(C5:C16),C5:C16,0))) -> Janeiro
A53: Mês com maior saldo | D53: =IF(SUM(B5:B16)=0,"—",INDEX(A5:A16,MATCH(MAX(D5:D16),D5:D16,0))) -> —
A54: Categoria campeã do ano | D54: =IF(SUM(N22:N33)=0,"—",INDEX(A22:A33,MATCH(MAX(N22:N33),N22:N33,0))) -> Mercado
A55: Média mensal de saídas | D55: =IFERROR(AVERAGEIF(C5:C16,">0"),0) -> 649.6
A56: Total investido no ano | D56: =Investimento!$D$17 -> 0
A57: Taxa de poupança (Saldo ÷ Entradas) | D57: =IFERROR(D17/B17,0) -> 0

Sheet Metas Financeiras
A1: Metas Financeiras · Notinha
A3: METAS (preencha Meta, Valor alvo, Já guardado e Prazo)
A4: Meta | B4: Valor alvo | C4: Já guardado | D4: Falta | E4: % concluído | F4: Prazo
A5: Reserva de emergência (exemplo) | B5: 5000 | C5: 1500 | D5: =B5-C5 -> 3500 | E5: =IFERROR(C5/B5,0) -> 0.3 | F5: 46387
D6: =B6-C6 -> 0 | E6: =IFERROR(C6/B6,0) -> 0
D7: =B7-C7 -> 0 | E7: =IFERROR(C7/B7,0) -> 0
D8: =B8-C8 -> 0 | E8: =IFERROR(C8/B8,0) -> 0
D9: =B9-C9 -> 0 | E9: =IFERROR(C9/B9,0) -> 0
D10: =B10-C10 -> 0 | E10: =IFERROR(C10/B10,0) -> 0
D11: =B11-C11 -> 0 | E11: =IFERROR(C11/B11,0) -> 0
D12: =B12-C12 -> 0 | E12: =IFERROR(C12/B12,0) -> 0
D13: =B13-C13 -> 0 | E13: =IFERROR(C13/B13,0) -> 0
D14: =B14-C14 -> 0 | E14: =IFERROR(C14/B14,0) -> 0

Sheet Investimento
A1: Investimento · Notinha
A3: INVESTIMENTOS POR MÊS (puxa das abas mensais)
A4: Mês | B4: Reserva | C4: Renda fixa | D4: Total
A5: Janeiro | B5: =Janeiro!$I$42 -> 0 | C5: =Janeiro!$I$43 -> 0 | D5: =Janeiro!$I$44 -> 0
A6: Fevereiro | B6: =Fevereiro!$I$42 -> 0 | C6: =Fevereiro!$I$43 -> 0 | D6: =Fevereiro!$I$44 -> 0
A7: Março | B7: =Março!$I$42 -> 0 | C7: =Março!$I$43 -> 0 | D7: =Março!$I$44 -> 0
A8: Abril | B8: =Abril!$I$42 -> 0 | C8: =Abril!$I$43 -> 0 | D8: =Abril!$I$44 -> 0
A9: Maio | B9: =Maio!$I$42 -> 0 | C9: =Maio!$I$43 -> 0 | D9: =Maio!$I$44 -> 0
A10: Junho | B10: =Junho!$I$42 -> 0 | C10: =Junho!$I$43 -> 0 | D10: =Junho!$I$44 -> 0
A11: Julho | B11: =Julho!$I$42 -> 0 | C11: =Julho!$I$43 -> 0 | D11: =Julho!$I$44 -> 0
A12: Agosto | B12: =Agosto!$I$42 -> 0 | C12: =Agosto!$I$43 -> 0 | D12: =Agosto!$I$44 -> 0
A13: Setembro | B13: =Setembro!$I$42 -> 0 | C13: =Setembro!$I$43 -> 0 | D13: =Setembro!$I$44 -> 0
A14: Outubro | B14: =Outubro!$I$42 -> 0 | C14: =Outubro!$I$43 -> 0 | D14: =Outubro!$I$44 -> 0
A15: Novembro | B15: =Novembro!$I$42 -> 0 | C15: =Novembro!$I$43 -> 0 | D15: =Novembro!$I$44 -> 0
A16: Dezembro | B16: =Dezembro!$I$42 -> 0 | C16: =Dezembro!$I$43 -> 0 | D16: =Dezembro!$I$44 -> 0
A17: TOTAL DO ANO | B17: =SUM(B5:B16) -> 0 | C17: =SUM(C5:C16) -> 0 | D17: =SUM(D5:D16) -> 0
